caprazli_provenance.py
ots_stamp.py
caprazli_provenance-1.0.0.dist-info/licenses/LICENSE
caprazli_provenance-1.0.0.dist-info/licenses/LICENSE.proof.ots
caprazli_provenance-1.0.0.dist-info/METADATA
caprazli_provenance-1.0.0.dist-info/WHEEL
caprazli_provenance-1.0.0.dist-info/entry_points.txt
caprazli_provenance-1.0.0.dist-info/top_level.txt
caprazli_provenance-1.0.0.dist-info/RECORD
