Metadata-Version: 2.4
Name: caprazli-provenance
Version: 1.0.0
Summary: Cryptographic priority claims for independent researchers via Bitcoin timestamps
Author-email: "Kafkas M. Caprazli" <caprazli@gmail.com>
License: CC-BY-4.0
Project-URL: Homepage, https://github.com/capraCoder/caprazli-provenance
Project-URL: Documentation, https://github.com/capraCoder/caprazli-provenance#readme
Project-URL: Repository, https://github.com/capraCoder/caprazli-provenance
Project-URL: Issues, https://github.com/capraCoder/caprazli-provenance/issues
Project-URL: DOI, https://doi.org/10.5281/zenodo.18115235
Keywords: provenance,timestamping,bitcoin,opentimestamps,independent-research,priority-claims
Classifier: Development Status :: 4 - Beta
Classifier: Intended Audience :: Science/Research
Classifier: License :: OSI Approved
Classifier: Operating System :: OS Independent
Classifier: Programming Language :: Python :: 3
Classifier: Programming Language :: Python :: 3.8
Classifier: Programming Language :: Python :: 3.9
Classifier: Programming Language :: Python :: 3.10
Classifier: Programming Language :: Python :: 3.11
Classifier: Programming Language :: Python :: 3.12
Classifier: Topic :: Scientific/Engineering
Requires-Python: >=3.8
License-File: LICENSE
License-File: LICENSE.proof.ots
Requires-Dist: requests>=2.25.0
Provides-Extra: full
Requires-Dist: opentimestamps-client>=0.7.0; extra == "full"
Dynamic: license-file
